zermeloapi/__init__.py
zermeloapi-2023.8.23.16.31.24.dist-info/LICENSE
zermeloapi-2023.8.23.16.31.24.dist-info/METADATA
zermeloapi-2023.8.23.16.31.24.dist-info/WHEEL
zermeloapi-2023.8.23.16.31.24.dist-info/top_level.txt
zermeloapi-2023.8.23.16.31.24.dist-info/RECORD
