Metadata-Version: 2.1
Name: zermeloapi
Version: 2023.8.23.16.31.24
Summary: zermelo api
Author: b.vill
Author-email: villeriusborro@gmail.com
Classifier: Programming Language :: Python :: 3
Classifier: License :: OSI Approved :: MIT License
Classifier: Operating System :: OS Independent
Requires-Python: >=3.0
License-File: LICENSE
Requires-Dist: datetime
Requires-Dist: requests
